{"assets/arabic_logo.png":["assets/arabic_logo.png"],"assets/codes_text.png":["assets/codes_text.png"],"assets/codey_logo.png":["assets/codey_logo.png"],"assets/insta_logo.png":["assets/insta_logo.png"],"assets/small_logo.png":["assets/small_logo.png"],"assets/tik_logo.png":["assets/tik_logo.png"],"assets/tik_logo2.png":["assets/tik_logo2.png"],"assets/tiktok_logo.png":["assets/tiktok_logo.png"],"assets/x_logo.png":["assets/x_logo.png"],"packages/cupertino_icons/assets/CupertinoIcons.ttf":["packages/cupertino_icons/assets/CupertinoIcons.ttf"]}